disretrieve/__init__.py
disretrieve/disretrieve.py
disretrieve-0.0.2.dist-info/METADATA
disretrieve-0.0.2.dist-info/WHEEL
disretrieve-0.0.2.dist-info/top_level.txt
disretrieve-0.0.2.dist-info/RECORD
