Metadata-Version: 2.1
Name: disretrieve
Version: 0.0.2
Summary: Retrieving data from discord via token
Author: MrBlxck
Keywords: python,discord
Classifier: Operating System :: Microsoft :: Windows
